rtl/fullAdder.v
module fullAdder (
	input wire a, b, cin,
	output wire sum, cout
);

assign sum = a ^ b ^ cin;
assign cout = (a & b) | (cin & (a ^ b));

endmodule

rtl/fullAdderNb.v
module fullAdderNb #(parameter Width = 8) 
(
	input wire [Width-1:0] a,
	input wire [Width-1:0] b,
	input wire cin,
	output wire [Width-1:0] sum,
	output wire cout, V 
);

wire [Width-1:0] carry;

genvar i;
generate
	for (i = 0; i < Width; i = i + 1) begin
		if (i == 0) begin
			fullAdder fa0 (.sum(sum[i]), .a(a[i]), .b(b[i] ^ cin), .cin(cin), .cout(carry[i]));
		end else if (i == Width-1) begin
			fullAdder fa1 (.sum(sum[i]), .a(a[i]), .b(b[i] ^ cin), .cin(carry[i-1]), .cout(cout));
		end else begin
			fullAdder fa2 (.sum(sum[i]), .a(a[i]), .b(b[i] ^ cin), .cin(carry[i-1]), .cout(carry[i]));
		end
	end
endgenerate

xor (V, cout, carry[Width-2]);

endmodule

rtl/accumulator.v
module accumulator #(parameter Width = 8)
(
	input clk, rst, 
	input wire cin,
	input wire [Width-1:0] A,
	output reg overflow, carry,
	output reg [Width-1:0] sum
);

reg [Width-1:0] post_A;
wire [Width-1:0] pre_sum;
wire V, cout;

always @(posedge clk or negedge rst) begin
	if (rst == 0)
		post_A <= 0;
	else
		post_A <= A;
end

always @(posedge clk or negedge rst) begin
	if (rst == 0) 
		sum <= 0;
	else
		sum <= pre_sum;
end

fullAdderNb #(.Width(Width)) FANb (.sum(pre_sum), .a(sum), .b(post_A), .cin(cin), .cout(cout), .V(V));

always @(posedge clk or negedge rst) begin
	if (rst == 0) 
		overflow <= 0;
	else
		overflow <= V;
end

always @(posedge clk or negedge rst) begin
	if (rst == 0)
		carry <= 0;
	else 
		carry <= cout;
end

endmodule

dv/accumulator_tb.v
module accumulator_tb;

	`ifdef Width
        	parameter Width = `Width;
    	`else
        	parameter Width = 32;
    	`endif

	reg clk, rst;
	reg [Width-1:0] A;
	reg cin;

	wire overflow, carry;
	wire [Width-1:0] sum;
	wire [Width-1:0] pre_sum;

	integer i;

accumulator #(.Width(Width)) dut (.*);

initial begin
	$dumpfile ("accumulator_wave.vcd");
	$dumpvars (0, accumulator_tb);
	clk = 0;
	forever #1 clk = ~clk;
end

initial begin
	rst = 0;
	cin = 0;

	#1;
	rst = 1;	
	A = 1;

	@(posedge clk)
	$display (" ");
	$display ("Test case 1: cin = %d,  Width = %d", cin, Width);

	for (i = 0; i < (1 << Width); i = i + 1) begin
		@(posedge clk)
		if ((overflow == 1) & (carry == 1)) begin
			$display ("A = %d, S = %d, overflow = %d, carry: %d. DETECT BOTH OVERFLOW AND CARRY", A, sum, overflow, carry);	
		end else if (overflow == 1) begin
			$display ("A = %d, S = %d, overflow = %d, carry: %d. DETECT OVERFLOW", A, sum, overflow, carry);
		end else if (carry == 1) begin
			$display ("A = %d, S = %d, overflow = %d, carry: %d. DETECT CARRY", A, sum, overflow, carry);
		end else
			$display ("A = %d, S = %d, overflow = %d, carry: %d", A, sum, overflow, carry);
	end

	#1;
	rst = 0;

	#1;
	rst = 1;
	cin = 1;	
	A = 1;

	@(posedge clk)
	$display (" ");
	$display ("Test case 1: cin = %d,  Width = %d", cin, Width);
	
	for (i = 0; i < (1 << Width); i = i + 1) begin
		@(posedge clk)
		if ((overflow == 1) & (carry == 1)) begin
			$display ("A = %d, S = %d, overflow = %d, carry: %d. DETECT BOTH OVERFLOW AND CARRY", A, sum, overflow, carry);	
		end else if (overflow == 1) begin
			$display ("A = %d, S = %d, overflow = %d, carry: %d. DETECT OVERFLOW", A, sum, overflow, carry);
		end else if (carry == 1) begin
			$display ("A = %d, S = %d, overflow = %d, carry: %d. DETECT CARRY", A, sum, overflow, carry);
		end else
			$display ("A = %d, S = %d, overflow = %d, carry: %d", A, sum, overflow, carry);
	end
		
	#50;
	$finish;
end

endmodule

sim/accumulator_wave.vcd
$date
	Mon Sep 16 19:21:12 2024
$end
$version
	Icarus Verilog
$end
$timescale
	1s
$end
$scope module accumulator_tb $end
$var wire 4 ! sum [3:0] $end
$var wire 1 " overflow $end
$var wire 1 # carry $end
$var parameter 32 $ Width $end
$var reg 4 % A [3:0] $end
$var reg 1 & cin $end
$var reg 1 ' clk $end
$var reg 1 ( rst $end
$var integer 32 ) i [31:0] $end
$scope module dut $end
$var wire 4 * A [3:0] $end
$var wire 1 & cin $end
$var wire 1 ' clk $end
$var wire 1 ( rst $end
$var wire 4 + pre_sum [3:0] $end
$var wire 1 , cout $end
$var wire 1 - V $end
$var parameter 32 . Width $end
$var reg 1 # carry $end
$var reg 1 " overflow $end
$var reg 4 / post_A [3:0] $end
$var reg 4 0 sum [3:0] $end
$scope module FANb $end
$var wire 1 - V $end
$var wire 4 1 a [3:0] $end
$var wire 4 2 b [3:0] $end
$var wire 1 & cin $end
$var wire 4 3 sum [3:0] $end
$var wire 1 , cout $end
$var wire 4 4 carry [3:0] $end
$var parameter 32 5 Width $end
$scope begin genblk1[0] $end
$var parameter 2 6 i $end
$scope begin genblk1 $end
$scope module fa0 $end
$var wire 1 7 a $end
$var wire 1 8 b $end
$var wire 1 & cin $end
$var wire 1 9 cout $end
$var wire 1 : sum $end
$upscope $end
$upscope $end
$upscope $end
$scope begin genblk1[1] $end
$var parameter 2 ; i $end
$scope begin genblk1 $end
$scope module fa2 $end
$var wire 1 < a $end
$var wire 1 = b $end
$var wire 1 > cin $end
$var wire 1 ? cout $end
$var wire 1 @ sum $end
$upscope $end
$upscope $end
$upscope $end
$scope begin genblk1[2] $end
$var parameter 3 A i $end
$scope begin genblk1 $end
$scope module fa2 $end
$var wire 1 B a $end
$var wire 1 C b $end
$var wire 1 D cin $end
$var wire 1 E cout $end
$var wire 1 F sum $end
$upscope $end
$upscope $end
$upscope $end
$scope begin genblk1[3] $end
$var parameter 3 G i $end
$scope begin genblk1 $end
$scope module fa1 $end
$var wire 1 H a $end
$var wire 1 I b $end
$var wire 1 J cin $end
$var wire 1 , cout $end
$var wire 1 K sum $end
$upscope $end
$upscope $end
$upscope $end
$upscope $end
$upscope $end
$upscope $end
$enddefinitions $end
$comment Show the parameter values. $end
$dumpall
b11 G
b10 A
b1 ;
b0 6
b100 5
b100 .
b100 $
$end
#0
$dumpvars
0K
0J
0I
0H
0F
0E
0D
0C
0B
0@
0?
0>
0=
0<
0:
09
08
07
bz000 4
b0 3
b0 2
b0 1
b0 0
b0 /
0-
0,
b0 +
bx *
bx )
0(
0'
0&
bx %
0#
0"
b0 !
$end
#1
b1 +
b1 3
1:
18
b1 /
b1 2
b1 %
b1 *
1(
1'
#2
0'
#3
1@
1>
b10 +
b10 3
0:
bz001 4
19
17
b1 !
b1 0
b1 1
b0 )
1'
#4
0'
#5
0F
0D
0>
0?
1:
bz000 4
09
b11 +
b11 3
1@
07
1<
b10 !
b10 0
b10 1
b1 )
1'
#6
0'
#7
1F
1D
1?
0@
1>
b100 +
b100 3
0:
bz011 4
19
17
b11 !
b11 0
b11 1
b10 )
1'
#8
0'
#9
0-
0K
0D
0J
0>
0?
0E
1:
bz000 4
09
0@
b101 +
b101 3
1F
07
0<
1B
b100 !
b100 0
b100 1
b11 )
1'
#10
0'
#11
1@
1>
b110 +
b110 3
0:
bz001 4
19
17
b101 !
b101 0
b101 1
b100 )
1'
#12
0'
#13
0-
0K
0J
0E
1F
0D
0>
0?
1:
bz000 4
09
b111 +
b111 3
1@
07
1<
b110 !
b110 0
b110 1
b101 )
1'
#14
0'
#15
1-
1K
1J
1E
0F
1D
1?
0@
1>
b1000 +
b1000 3
0:
bz111 4
19
17
b111 !
b111 0
b111 1
b110 )
1'
#16
0'
#17
0D
0J
0-
0>
0?
0E
0,
1:
bz000 4
09
0@
0F
b1001 +
b1001 3
1K
07
0<
0B
1H
1"
b1000 !
b1000 0
b1000 1
b111 )
1'
#18
0'
#19
1@
1>
b1010 +
b1010 3
0:
bz001 4
19
17
b1001 !
b1001 0
b1001 1
0"
b1000 )
1'
#20
0'
#21
0F
0D
0>
0?
1:
bz000 4
09
b1011 +
b1011 3
1@
07
1<
b1010 !
b1010 0
b1010 1
b1001 )
1'
#22
0'
#23
1F
1D
1?
0@
1>
b1100 +
b1100 3
0:
bz011 4
19
17
b1011 !
b1011 0
b1011 1
b1010 )
1'
#24
0'
#25
0,
0-
1K
0D
0J
0>
0?
0E
1:
bz000 4
09
0@
b1101 +
b1101 3
1F
07
0<
1B
b1100 !
b1100 0
b1100 1
b1011 )
1'
#26
0'
#27
1@
1>
b1110 +
b1110 3
0:
bz001 4
19
17
b1101 !
b1101 0
b1101 1
b1100 )
1'
#28
0'
#29
0,
0-
1K
0J
0E
1F
0D
0>
0?
1:
bz000 4
09
b1111 +
b1111 3
1@
07
1<
b1110 !
b1110 0
b1110 1
b1101 )
1'
#30
0'
#31
1,
0-
0K
1J
1E
0F
1D
1?
0@
1>
b0 +
b0 3
0:
bz111 4
19
17
b1111 !
b1111 0
b1111 1
b1110 )
1'
#32
0'
#33
0D
0J
0-
0>
0?
0E
0,
1:
bz000 4
09
0@
0F
b1 +
b1 3
0K
07
0<
0B
0H
1#
b0 !
b0 0
b0 1
b1111 )
1'
#34
0'
#35
1@
1>
b10 +
b10 3
0:
bz001 4
19
17
b1 !
b1 0
b1 1
0#
b10000 )
1'
#36
b0 +
b0 3
0@
0>
bz000 4
09
08
07
b0 !
b0 0
b0 1
b0 /
b0 2
0(
0'
#37
b1 /
b1 2
0,
0-
0J
0E
0D
0?
0>
bz000 4
09
1@
1F
1K
08
b1111 +
b1111 3
1:
1=
1C
1I
1&
1(
1'
#38
0'
#39
1>
19
1D
1J
0-
0:
1@
1?
1F
bz111 4
1E
b1110 +
b1110 3
1K
1,
17
1<
1B
1H
b1111 !
b1111 0
b1111 1
b0 )
1'
#40
0'
#41
0@
0>
bz110 4
09
b1101 +
b1101 3
1:
07
b1110 !
b1110 0
b1110 1
1#
b1 )
1'
#42
0'
#43
1>
1F
19
1D
0:
b1100 +
b1100 3
0@
bz111 4
1?
17
0<
b1101 !
b1101 0
b1101 1
b10 )
1'
#44
0'
#45
0F
0D
0?
1@
0>
bz100 4
09
b1011 +
b1011 3
1:
07
b1100 !
b1100 0
b1100 1
b11 )
1'
#46
0'
#47
1>
0-
1K
19
1D
1J
0:
1@
1?
b1010 +
b1010 3
0F
bz111 4
1E
17
1<
0B
b1011 !
b1011 0
b1011 1
b100 )
1'
#48
0'
#49
0@
0>
bz110 4
09
b1001 +
b1001 3
1:
07
b1010 !
b1010 0
b1010 1
b101 )
1'
#50
0'
#51
0-
1K
1J
1E
1>
0F
19
1D
0:
b1000 +
b1000 3
0@
bz111 4
1?
17
0<
b1001 !
b1001 0
b1001 1
b110 )
1'
#52
0'
#53
1-
0K
0J
0E
1F
0D
0?
1@
0>
bz000 4
09
b111 +
b111 3
1:
07
b1000 !
b1000 0
b1000 1
b111 )
1'
#54
0'
#55
1>
19
1D
1J
0-
0:
1@
1?
1F
bz111 4
1E
b110 +
b110 3
0K
1,
17
1<
1B
0H
1"
b111 !
b111 0
b111 1
b1000 )
1'
#56
0'
#57
0@
0>
bz110 4
09
b101 +
b101 3
1:
07
b110 !
b110 0
b110 1
0"
b1001 )
1'
#58
0'
#59
1>
1F
19
1D
0:
b100 +
b100 3
0@
bz111 4
1?
17
0<
b101 !
b101 0
b101 1
b1010 )
1'
#60
0'
#61
0F
0D
0?
1@
0>
bz100 4
09
b11 +
b11 3
1:
07
b100 !
b100 0
b100 1
b1011 )
1'
#62
0'
#63
1,
1>
0-
0K
19
1D
1J
0:
1@
1?
b10 +
b10 3
0F
bz111 4
1E
17
1<
0B
b11 !
b11 0
b11 1
b1100 )
1'
#64
0'
#65
0@
0>
bz110 4
09
b1 +
b1 3
1:
07
b10 !
b10 0
b10 1
b1101 )
1'
#66
0'
#67
1,
0-
0K
1J
1E
1>
0F
19
1D
0:
b0 +
b0 3
0@
bz111 4
1?
17
0<
b1 !
b1 0
b1 1
b1110 )
1'
#68
0'
#69
0,
0-
1K
0J
0E
1F
0D
0?
1@
0>
bz000 4
09
b1111 +
b1111 3
1:
07
b0 !
b0 0
b0 1
b1111 )
1'
#70
0'
#71
1>
19
1D
1J
0-
0:
1@
1?
1F
bz111 4
1E
b1110 +
b1110 3
1K
1,
17
1<
1B
1H
0#
b1111 !
b1111 0
b1111 1
b10000 )
1'
#72
0'
#73
0@
0>
bz110 4
09
b1101 +
b1101 3
1:
07
b1110 !
b1110 0
b1110 1
1#
1'
#74
0'
#75
1>
1F
19
1D
0:
b1100 +
b1100 3
0@
bz111 4
1?
17
0<
b1101 !
b1101 0
b1101 1
1'
#76
0'
#77
0F
0D
0?
1@
0>
bz100 4
09
b1011 +
b1011 3
1:
07
b1100 !
b1100 0
b1100 1
1'
#78
0'
#79
1>
0-
1K
19
1D
1J
0:
1@
1?
b1010 +
b1010 3
0F
bz111 4
1E
17
1<
0B
b1011 !
b1011 0
b1011 1
1'
#80
0'
#81
0@
0>
bz110 4
09
b1001 +
b1001 3
1:
07
b1010 !
b1010 0
b1010 1
1'
#82
0'
#83
0-
1K
1J
1E
1>
0F
19
1D
0:
b1000 +
b1000 3
0@
bz111 4
1?
17
0<
b1001 !
b1001 0
b1001 1
1'
#84
0'
#85
1-
0K
0J
0E
1F
0D
0?
1@
0>
bz000 4
09
b111 +
b111 3
1:
07
b1000 !
b1000 0
b1000 1
1'
#86
0'
#87
1>
19
1D
1J
0-
0:
1@
1?
1F
bz111 4
1E
b110 +
b110 3
0K
1,
17
1<
1B
0H
1"
b111 !
b111 0
b111 1
1'
#88
0'
#89
0@
0>
bz110 4
09
b101 +
b101 3
1:
07
b110 !
b110 0
b110 1
0"
1'
#90
0'
#91
1>
1F
19
1D
0:
b100 +
b100 3
0@
bz111 4
1?
17
0<
b101 !
b101 0
b101 1
1'
#92
0'
#93
0F
0D
0?
1@
0>
bz100 4
09
b11 +
b11 3
1:
07
b100 !
b100 0
b100 1
1'
#94
0'
#95
1,
1>
0-
0K
19
1D
1J
0:
1@
1?
b10 +
b10 3
0F
bz111 4
1E
17
1<
0B
b11 !
b11 0
b11 1
1'
#96
0'
#97
0@
0>
bz110 4
09
b1 +
b1 3
1:
07
b10 !
b10 0
b10 1
1'
#98
0'
#99
1,
0-
0K
1J
1E
1>
0F
19
1D
0:
b0 +
b0 3
0@
bz111 4
1?
17
0<
b1 !
b1 0
b1 1
1'
#100
0'
#101
0,
0-
1K
0J
0E
1F
0D
0?
1@
0>
bz000 4
09
b1111 +
b1111 3
1:
07
b0 !
b0 0
b0 1
1'
#102
0'
#103
1>
19
1D
1J
0-
0:
1@
1?
1F
bz111 4
1E
b1110 +
b1110 3
1K
1,
17
1<
1B
1H
0#
b1111 !
b1111 0
b1111 1
1'
#104
0'
#105
0@
0>
bz110 4
09
b1101 +
b1101 3
1:
07
b1110 !
b1110 0
b1110 1
1#
1'
#106
0'
#107
1>
1F
19
1D
0:
b1100 +
b1100 3
0@
bz111 4
1?
17
0<
b1101 !
b1101 0
b1101 1
1'
#108
0'
#109
0F
0D
0?
1@
0>
bz100 4
09
b1011 +
b1011 3
1:
07
b1100 !
b1100 0
b1100 1
1'
#110
0'
#111
1>
0-
1K
19
1D
1J
0:
1@
1?
b1010 +
b1010 3
0F
bz111 4
1E
17
1<
0B
b1011 !
b1011 0
b1011 1
1'
#112
0'
#113
0@
0>
bz110 4
09
b1001 +
b1001 3
1:
07
b1010 !
b1010 0
b1010 1
1'
#114
0'
#115
0-
1K
1J
1E
1>
0F
19
1D
0:
b1000 +
b1000 3
0@
bz111 4
1?
17
0<
b1001 !
b1001 0
b1001 1
1'
#116
0'
#117
1-
0K
0J
0E
1F
0D
0?
1@
0>
bz000 4
09
b111 +
b111 3
1:
07
b1000 !
b1000 0
b1000 1
1'
#118
0'
#119
1>
19
1D
1J
0-
0:
1@
1?
1F
bz111 4
1E
b110 +
b110 3
0K
1,
17
1<
1B
0H
1"
b111 !
b111 0
b111 1
1'
#120
0'
#121
0@
0>
bz110 4
09
b101 +
b101 3
1:
07
b110 !
b110 0
b110 1
0"
1'
